ilovepdf/__init__.py
ilovepdf/abstract_task_element.py
ilovepdf/compress_task.py
ilovepdf/extract_task.py
ilovepdf/file.py
ilovepdf/htmltopdf_task.py
ilovepdf/ilovepdf_api.py
ilovepdf/imagepdf_task.py
ilovepdf/merge_task.py
ilovepdf/office_pdf_task.py
ilovepdf/pdfocr_task.py
ilovepdf/pdftopdfa_task.py
ilovepdf/protect_task.py
ilovepdf/repair_task.py
ilovepdf/rotate_task.py
ilovepdf/sign_task.py
ilovepdf/split_task.py
ilovepdf/task.py
ilovepdf/unlock_task.py
ilovepdf/watermark_task.py
ilovepdf/exceptions/__init__.py
ilovepdf/exceptions/auth_exception.py
ilovepdf/exceptions/base_custom_exception.py
ilovepdf/exceptions/choice_errors.py
ilovepdf/exceptions/download_exception.py
ilovepdf/exceptions/file_errors.py
ilovepdf/exceptions/float_errors.py
ilovepdf/exceptions/int_errors.py
ilovepdf/exceptions/not_implemented_exception.py
ilovepdf/exceptions/path_exception.py
ilovepdf/exceptions/payload_field_errors.py
ilovepdf/exceptions/process_exception.py
ilovepdf/exceptions/signature_exception.py
ilovepdf/exceptions/start_exception.py
ilovepdf/exceptions/task_exception.py
ilovepdf/exceptions/upload_exception.py
ilovepdf/sign/__init__.py
ilovepdf/sign/element.py
ilovepdf/sign/signer.py
ilovepdf/sign/signer_file.py
ilovepdf/validators/__init__.py
ilovepdf/validators/bool_validator.py
ilovepdf/validators/choice_validator.py
ilovepdf/validators/date_validator.py
ilovepdf/validators/float_validator.py
ilovepdf/validators/int_validator.py
ilovepdf/validators/string_validator.py
samples/compress_advanced.py
samples/compress_basic.py
samples/extract_basic.py
samples/html_to_pdf_basic.py
samples/imagepdf_basic.py
samples/merge_basic.py
samples/office_pdf_basic.py
samples/pdfocr_basic.py
samples/pdftopdfa_advanced.py
samples/pdftopdfa_basic.py
samples/protect_basic.py
samples/repair_basic.py
samples/rotate_basic.py
samples/sign_advanced.py
samples/sign_basic.py
samples/split_advanced.py
samples/split_advanced_merge.py
samples/split_basic.py
samples/watermark_advanced.py
ilovepdf-0.0.1.dist-info/METADATA
ilovepdf-0.0.1.dist-info/WHEEL
ilovepdf-0.0.1.dist-info/top_level.txt
ilovepdf-0.0.1.dist-info/RECORD
