Metadata-Version: 2.4
Name: ilovepdf
Version: 0.0.1
Summary: iLovePDF Python API
Author-email: ilovepdf <info@ilovepdf.com>
Project-URL: Documentation, https://developer.ilovepdf.com/docs
Project-URL: Homepage, https://ilovepdf.com/
Requires-Python: <=3.14.2,>=3.10
Requires-Dist: requests>=2.28.0
Requires-Dist: pyjwt>=2.4.0
